AT24Cxxx/AT24Cxxx.py
AT24Cxxx/__init__.py
AT24Cxxx-0.1.1.dist-info/METADATA
AT24Cxxx-0.1.1.dist-info/WHEEL
AT24Cxxx-0.1.1.dist-info/top_level.txt
AT24Cxxx-0.1.1.dist-info/RECORD
